wilt/__init__.py
wilt/__main__.py
wilt/cli.py
wilt/resdb.py
wilt/test.py
wilt/utility.py
wilt/ci/__init__.py
wilt/ci/gitlab.py
wilt/ci/rest.py
wilt/cq/__init__.py
wilt/cq/wilt.py
Wilt-0.0.2.dist-info/METADATA
Wilt-0.0.2.dist-info/WHEEL
Wilt-0.0.2.dist-info/entry_points.txt
Wilt-0.0.2.dist-info/top_level.txt
Wilt-0.0.2.dist-info/RECORD
