Metadata-Version: 2.1
Name: Wilt
Version: 0.0.2
Summary: Architect's collection of codebase health probes
Home-page: https://heptapod.host/saajns/wilt
Author: saaj
Author-email: mail@saaj.me
License: GPL-3.0-or-later
Keywords: code-metrics code-quality continuous-integration
Classifier: Environment :: Console
Classifier: Intended Audience :: Developers
Classifier: Topic :: Software Development :: Quality Assurance
Classifier: Programming Language :: Python :: 3
Classifier: Programming Language :: Python :: 3.10
Classifier: Programming Language :: Python :: 3.11
Classifier: Programming Language :: Python :: 3.12
Classifier: Programming Language :: Python :: 3 :: Only
Requires-Python: >= 3.10
Requires-Dist: pandas <3,>=2.2.2
Requires-Dist: plotly <6,>=5.22.0
Requires-Dist: requests <3,>=2.32.3
Requires-Dist: tqdm <5,>=4.66.4
